whlctl/__init__.py
whlctl/cli.py
whlctl/whlctl.py
whlctl-0.1.1.dist-info/entry_points.txt
whlctl-0.1.1.dist-info/LICENSE
whlctl-0.1.1.dist-info/WHEEL
whlctl-0.1.1.dist-info/METADATA
whlctl-0.1.1.dist-info/RECORD
