Metadata-Version: 2.1
Name: whlctl
Version: 0.1.1
Summary: WartHog Lights ConTroL
Author-email: Karim Vergnes <me@thesola.io>
Classifier: Development Status :: 4 - Beta
Classifier: Operating System :: POSIX :: Linux
Classifier: Intended Audience :: End Users/Desktop
Classifier: Intended Audience :: Developers
Classifier: Topic :: Utilities
Classifier: Topic :: Games/Entertainment :: Simulation
Classifier: Topic :: System :: Hardware :: Universal Serial Bus (USB) :: Human Interface Device (HID)
Requires-Dist: docopt
Project-URL: Source, https://github.com/Thesola10/whlctl
